[
    {
        "0":":تاظحلام"
    },
    {
        "0":"..........................................................................................................................................................................................................\n...................................................................................................................................................."
    },
    {
        "0":"رارقأ"
    },
    {
        "0":"لمحتأو ،ةحيحص عئاقوو تانايب يه ،قفرلما  ىوكشلا\/ملظتلا يف ةدراولا عئاقولا ةفاكو ،هلاعأ ةدراولا تانايبلا عيمج نأب هاندأ عقولما انأ رقأ\n.كلذ فلاخ ةلاح يف ةينوناقلا ةيلوؤسلما"
    },
    {
        "0":"كرحتلما فتاهلا\nيكتشلما \/ ملظتلا عيقوت"
    },
    {
        "0":"عيقوتلا\nصتخلما فظولما"
    }
]